clera/__init__.py
clera/core.py
clera/database.py
clera/widgets.py
clera/icons/__init__.py
clera/icons/data.py
clera/scripts/__init__.py
clera/scripts/deploy.py
clera/scripts/editor.py
clera/stubs/__init__.pyi
clera/stubs/core.pyi
clera/stubs/database.pyi
clera/stubs/handlers.pyi
clera/stubs/widgets.pyi
clera/utils/__init__.py
clera/utils/exceptions.py
clera/utils/handlers.py
clera/utils/keys.py
clera/utils/procr.py
clera/utils/style.py
clera-0.2.2.dist-info/LICENCE.txt
clera-0.2.2.dist-info/METADATA
clera-0.2.2.dist-info/WHEEL
clera-0.2.2.dist-info/entry_points.txt
clera-0.2.2.dist-info/top_level.txt
clera-0.2.2.dist-info/RECORD
