Metadata-Version: 2.1
Name: clera
Version: 0.2.2
Summary: Write Simple and Quick Python GUI Application
Author: Erasmus A. Junior
Author-email: eirasmx@pm.me
License: GNU LGPLv3
Keywords: gui,clera,simple,simplegui,pyside,pyside6,python,easy
Classifier: Development Status :: 3 - Alpha
Classifier: Environment :: Console
Classifier: Intended Audience :: Developers
Classifier: License :: OSI Approved :: GNU Lesser General Public License v3 (LGPLv3)
Classifier: Operating System :: OS Independent
Classifier: Programming Language :: Python :: 3
Requires-Python: >=3.7
License-File: LICENCE.txt
Requires-Dist: PySide6
